{"id":"tt0370263","title":"AVP: Alien vs. Predator","rating":5.6,"rating_count":195000,"release_year":2004,"popularity":3115,"imdb_type":"movie","runtime":"1h 41m","genres":["Action","Adventure","Horror","Sci-Fi","Thriller"],"countries":["United States","United Kingdom","Czech Republic","Canada","Germany"],"languages":["English","Italian"],"director_names":["Paul W.S. Anderson"],"creator_names":[],"description":"When a private satellite encounters an unidentified source of heat in Antarctica and it is found to be a pyramid buried deep underground , a search team comprising of top-of-the-line archaeologists and engineers is sent to Antarctica to find out more . Once there , the team comes across signs which indicate that the place is inhabited by an unknown alien species . It is not long before the aliens begin to hunt the team members . At the same time , a trio of coming-of-age Predators have arrived to collect the skulls of the aliens as trophies , and the humans are caught between a deadly battle between the two warring species .","aka":["Alien vs. Predator"],"version":2,"image":"https://m.media-amazon.com/images/M/MV5BMTU4MjIwMTcyMl5BMl5BanBnXkFtZTYwMTYwNDA3._V1_QL75_UX190_CR0,0,190,281_FMwebp.webp","imdb_date":"2004-10-22","actors":[{"id":"nm0005125","name":"Sanaa Lathan"},{"id":"nm0000448","name":"Lance Henriksen"},{"id":"nm0100556","name":"Raoul Bova"},{"id":"nm0001971","name":"Ewen Bremner"},{"id":"nm0758760","name":"Colin Salmon"},{"id":"nm0281107","name":"Tommy Flanagan"},{"id":"nm0753229","name":"Joseph Rye"},{"id":"nm0209169","name":"Agathe de La Boulaye"},{"id":"nm0635297","name":"Carsten Norgaard"},{"id":"nm0873744","name":"Sam Troughton"},{"id":"nm1362893","name":"Petr Jákl"},{"id":"nm0974339","name":"Pavel Bezdek"},{"id":"nm1240908","name":"Kieran Bew"},{"id":"nm0901088","name":"Carsten Voigt"},{"id":"nm0277041","name":"Jan Filipenský"},{"id":"nm1345685","name":"Adrian Bouchet"},{"id":"nm0524075","name":"Andy Lucas"},{"id":"nm0108510","name":"Liz May Brice"}]}