{"id":"tt11827628","title":"Memory","rating":5.7,"rating_count":20000,"release_year":2022,"popularity":64,"imdb_type":"movie","runtime":"1h 54m","genres":[],"countries":["United States"],"languages":["English"],"director_names":["Martin Campbell"],"creator_names":[],"description":"","aka":["Флешбек"],"version":2,"image":"https://m.media-amazon.com/images/M/MV5BOGI5N2FhNzktZjZlNi00MmRjLWE1MmUtNjRlNzQyOGMzYjNhXkEyXkFqcGdeQXVyMDA4NzMyOA@@._V1_QL75_UX190_CR0,0,190,281_.jpg","imdb_date":"2022-04-29","actors":[{"id":"nm0000553","name":"Liam Neeson"},{"id":"nm0001602","name":"Guy Pearce"},{"id":"nm4883026","name":"Taj Atwal"},{"id":"nm2386306","name":"Harold Torres"},{"id":"nm0269909","name":"Ray Fearon"},{"id":"nm0000899","name":"Monica Bellucci"},{"id":"nm0829032","name":"Ray Stevenson"},{"id":"nm5113028","name":"Mia Sanchez"},{"id":"nm9978432","name":"Daniel De Bourg"},{"id":"nm1653488","name":"Natalie Anderson"},{"id":"nm3072339","name":"Rebecca Calder"},{"id":"nm0931656","name":"Scot Williams"},{"id":"nm0710542","name":"Doug Rao"},{"id":"nm1284482","name":"Atanas Srebrev"},{"id":"nm0090196","name":"Lee Boardman"},{"id":"nm2706152","name":"Stella Stocker"},{"id":"nm3386410","name":"Josh Taylor"},{"id":"nm2085345","name":"Vladimir Mihaylov"}]}