{"id":"tt1278340","title":"Død snø","rating":6.3,"rating_count":67000,"release_year":2009,"popularity":null,"imdb_type":"movie","runtime":"1h 32m","genres":["Comedy","Fantasy","Horror"],"countries":["Norway"],"languages":["English","Norwegian"],"director_names":["Tommy Wirkola"],"creator_names":[],"description":"Several friends take to the mountains and shack-up in the wilderness of back-of-beyond to enjoy a little R and R together. Their peace is soon interrupted by a mysterious old man who informs them that during WWII, Nazi invaders of the area were brutal and harsh in their methods of control until, according to a legend, a villager's revolt drove the invaders up into the cold, dark mountains, where they perished. But now there's the rumor that they returned in the form of zombies --evil Nazi zombies.","aka":["Dead Snow"],"version":2,"image":"https://m.media-amazon.com/images/M/MV5BMTQyMjg0NDk3Nl5BMl5BanBnXkFtZTcwNzA5Nzk0Mg@@._V1_QL75_UY281_CR4,0,190,281_.jpg","imdb_date":"2009-01-09","actors":[{"id":"nm1355643","name":"Jeppe Beck Laursen"},{"id":"nm2297067","name":"Charlotte Frogner"},{"id":"nm0803928","name":"Jenny Skavlan"},{"id":"nm0388473","name":"Geir Vegar Hoel"},{"id":"nm2552337","name":"Stig Frode Henriksen"},{"id":"nm1284656","name":"Lasse Valdal"},{"id":"nm1284277","name":"Evy Kasseth Røsten"},{"id":"nm1335996","name":"Ane Dahl Torp"},{"id":"nm0839209","name":"Bjørn Sundquist"},{"id":"nm2505635","name":"Ørjan Gamst"},{"id":"nm3135934","name":"Steinar Kaarstein"},{"id":"nm12428142","name":"Lars Eivind Lund"},{"id":"nm4741564","name":"Caroline Thielemann"},{"id":"nm2482088","name":"Tommy Wirkola"}]}