{"id":"tt1234719","title":"Red Dawn","rating":5.3,"rating_count":77000,"release_year":2012,"popularity":2449,"imdb_type":"movie","runtime":"1h 33m","genres":["Action","Drama"],"countries":["United States"],"languages":["English","Korean"],"director_names":["Dan Bradley"],"creator_names":[],"description":"The city of Spokane, Washington is awakened by a North Korean paratrooper invasion. Marine Corps veteran Jed Eckert and his civilian brother, Matt, escape with a group of friends to an isolated cabin in the woods, where they witness the execution of their father at the hands of the ruthless Captain Cho. The brothers unite with their friends to form a guerrilla resistance group--the Wolverines--to drive the invaders from their home.","aka":["Amenaza roja"],"version":2,"image":"https://m.media-amazon.com/images/M/MV5BMjI0MDAwMzA1M15BMl5BanBnXkFtZTcwNzIxMjY3OA@@._V1_QL75_UX190_CR0,0,190,281_.jpg","imdb_date":"2013-03-15","actors":[{"id":"nm1165110","name":"Chris Hemsworth"},{"id":"nm1456970","name":"Isabel Lucas"},{"id":"nm1242688","name":"Josh Hutcherson"},{"id":"nm0669681","name":"Josh Peck"},{"id":"nm1597316","name":"Adrianne Palicki"},{"id":"nm2982067","name":"Connor Cruise"},{"id":"nm0388064","name":"Edwin Hodge"},{"id":"nm0191442","name":"Brett Cullen"},{"id":"nm1595801","name":"Alyssa Diaz"},{"id":"nm2959119","name":"Julian Alcaraz"},{"id":"nm0498449","name":"Will Yun Lee"},{"id":"nm0604742","name":"Jeffrey Dean Morgan"},{"id":"nm0157312","name":"Fernando Chien"},{"id":"nm0158846","name":"Kenneth Choi"},{"id":"nm0313902","name":"Matt Gerald"},{"id":"nm5371700","name":"Michael A. Knight"},{"id":"nm3924692","name":"Steve Lenz"},{"id":"nm3340061","name":"Noah Smith"}]}