{
    "id": "tt1734493",
    "title": "Unlocked",
    "rating": 6.3,
    "rating_count": 34000,
    "release_year": 2017,
    "popularity": 3803,
    "imdb_type": "movie",
    "runtime": "1h 38m",
    "genres": [
        "Action",
        "Thriller"
    ],
    "countries": [
        "Czech Republic",
        "Switzerland",
        "United Kingdom",
        "United States",
        "France"
    ],
    "languages": [
        "English",
        "Arabic",
        "German",
        "Russian",
        "Czech"
    ],
    "director_names": [
        "Michael Apted"
    ],
    "creator_names": [],
    "description": "A CIA interrogator is lured into a ruse that puts London at risk of a biological attack.",
    "aka": [
        "Điệp Vụ Phản Gián"
    ],
    "version": 2,
    "image": "https://m.media-amazon.com/images/M/MV5BZWJiNGQ1YzgtOGVjZS00MGRjLTgwZDMtNWFiNmQ2ZWI1ZWNkXkEyXkFqcGdeQXVyMjM4NTM5NDY@._V1_QL75_UX190_CR0,6,190,281_.jpg",
    "imdb_date": "2017-05-05",
    "actors": [
        {
            "id": "nm0636426",
            "name": "Noomi Rapace"
        },
        {
            "id": "nm0089217",
            "name": "Orlando Bloom"
        },
        {
            "id": "nm0001057",
            "name": "Toni Collette"
        },
        {
            "id": "nm0000518",
            "name": "John Malkovich"
        },
        {
            "id": "nm0000140",
            "name": "Michael Douglas"
        },
        {
            "id": "nm0550624",
            "name": "Matthew Marsh"
        },
        {
            "id": "nm0403374",
            "name": "Makram Khoury"
        },
        {
            "id": "nm1340370",
            "name": "Brian Caspe"
        },
        {
            "id": "nm1527338",
            "name": "Philip Brodie"
        },
        {
            "id": "nm4108791",
            "name": "Tosin Cole"
        },
        {
            "id": "nm1981574",
            "name": "Michael Epp"
        },
        {
            "id": "nm3252163",
            "name": "Tom Reed"
        },
        {
            "id": "nm0214860",
            "name": "Raffaello Degruttola"
        },
        {
            "id": "nm4586939",
            "name": "Kevin Shen"
        },
        {
            "id": "nm3043480",
            "name": "Aymen Hamdouchi"
        },
        {
            "id": "nm4289673",
            "name": "Akshay Kumar"
        },
        {
            "id": "nm9523079",
            "name": "Robert Alexander Russell"
        },
        {
            "id": "nm6466615",
            "name": "Rami Nasr"
        }
    ]
}