{"id":"tt6456326","title":"Monsters of Man","rating":5.4,"rating_count":6500,"release_year":2020,"popularity":null,"imdb_type":"movie","runtime":"2h 11m","genres":["Action","Sci-Fi","Thriller"],"countries":["Australia"],"languages":["English"],"director_names":["Mark Toia"],"creator_names":[],"description":"A robotics company teams up with a corrupt CIA agent undergoing an illegal, unsanctioned military operation. Dropping four prototype robots into a suspected drug manufacturing camp in the Golden triangle that no one will miss. The mission is to prove the robotics company is worthy of winning a lucrative military contract. Six doctors on a good cause witness the brutal slaughter of an innocent village and are forced into a deadly game of cat and mouse as they become the new targets.","aka":["Inson yaratgan mahluqlar"],"version":2,"image":"https://m.media-amazon.com/images/M/MV5BYThhYTY4YTgtZDM4OS00ZDdiLWI5NTItMDBkYjc0ODM2MzU3XkEyXkFqcGdeQXVyNDQ0MDAxNQ@@._V1_QL75_UX190_CR0,2,190,281_FMwebp.webp","imdb_date":"2020-11-19","actors":[{"id":"nm0568180","name":"Neal McDonough"},{"id":"nm4275745","name":"Brett Tutor"},{"id":"nm1352774","name":"Jose Rosete"},{"id":"nm2617760","name":"David Haverty"},{"id":"nm4738395","name":"Paul Haapaniemi"},{"id":"nm2279545","name":"Ryan Hough"},{"id":"nm11780025","name":"Ly Ty"},{"id":"nm6508261","name":"Ma Rynet"},{"id":"nm7770979","name":"Kayli Tran"},{"id":"nm2971402","name":"Jessica Blackmore"},{"id":"nm6081832","name":"Jordy Tulleners"},{"id":"nm3725592","name":"Tatjana Marjanovic"},{"id":"nm5879783","name":"Conrad K. Pratt"},{"id":"nm1476891","name":"David Samartin"},{"id":"nm8801097","name":"Trong Kam"},{"id":"nm4976391","name":"Taylor Leigh Edwards"},{"id":"nm0998904","name":"Michael Goldman"}]}